extensionizer/__init__.py
extensionizer/manifest.py
extensionizer-0.0.2.dist-info/LICENSE.md
extensionizer-0.0.2.dist-info/METADATA
extensionizer-0.0.2.dist-info/WHEEL
extensionizer-0.0.2.dist-info/top_level.txt
extensionizer-0.0.2.dist-info/RECORD
