Metadata-Version: 2.1
Name: extensionizer
Version: 0.0.2
Summary: Python package to create chrome extensions quickly
Home-page: https://github.com/Yash182023/Manifest
Author: Yash Sharma
Author-email: yashsharmaat2004@gmail.com
Classifier: Programming Language :: Python :: 3
Classifier: License :: OSI Approved :: MIT License
Classifier: Operating System :: OS Independent
Requires-Python: >=3.6
License-File: LICENSE.md
